fastism/__init__.py
fastism/change_range.py
fastism/fast_ism.py
fastism/fast_ism_utils.py
fastism/flatten_model.py
fastism/ism_base.py
fastism/models/__init__.py
fastism/models/basset.py
fastism/models/bpnet.py
fastism/models/bpnet_dense.py
fastism/models/factorized_basset.py
fastism-0.5.1.dist-info/LICENSE
fastism-0.5.1.dist-info/WHEEL
fastism-0.5.1.dist-info/METADATA
fastism-0.5.1.dist-info/RECORD
