Metadata-Version: 2.1
Name: fastism
Version: 0.5.1
Summary: Fast In-silico Mutagenesis for Convolution-based Neural Networks
License: MIT
Author: Surag Nair
Author-email: surag@stanford.edu
Requires-Python: >=3.6,<4.0
Classifier: License :: OSI Approved :: MIT License
Classifier: Programming Language :: Python :: 3
Classifier: Programming Language :: Python :: 3.10
Classifier: Programming Language :: Python :: 3.6
Classifier: Programming Language :: Python :: 3.7
Classifier: Programming Language :: Python :: 3.8
Classifier: Programming Language :: Python :: 3.9
Requires-Dist: pydot (>=1.4.1,<2.0.0)
Requires-Dist: tensorflow (>=2.3.0,<3.0.0)
